Metadata-Version: 2.1
Name: brutelogger
Version: 0.1.2
Summary: A brutish file logger for when you just need to `tee` your screen.
Home-page: https://github.com/giuse/brutelogger
Author: Giuseppe Cuccu
Author-email: giuseppe.cuccu@gmail.com
License: MIT
Download-URL: https://github.com/giuse/brutelogger/archive/0.1.2.tar.gz
Project-URL: Bug Reports, https://github.com/giuse/brutelogger/issues
Project-URL: Source, https://github.com/giuse/brutelogger/
Keywords: logging tee
Platform: UNKNOWN
Classifier: Development Status :: 4 - Beta
Classifier: Intended Audience :: Developers
Classifier: Topic :: Software Development :: Build Tools
Classifier: License :: OSI Approved :: MIT License
Classifier: Programming Language :: Python :: 3 :: Only
Classifier: Programming Language :: Python :: 3.6
Classifier: Programming Language :: Python :: 3.7
Classifier: Programming Language :: Python :: 3.8
Requires-Python: >=3.6, <4
